[
  {
    "teamName": "Carolina Hurricanes",
    "expectedReturn": "21.10.2023",
    "playerName": "Sebastian Aho",
    "injuryStatus": "DAY-TO-DAY",
    "injuryReason": "Ylävartalo",
    "reportedDate": "19.10.2023",
    "report": "Aho (ylävartalo) ei ole käytettävissä torstain kilpailu vastaan Seattle, kohti Walt Ruff Hurricanes \"virallisella sivustolla."
  },
  {
    "teamName": "Florida Panthers",
    "expectedReturn": "12.12.2023",
    "playerName": "Brandon Montour",
    "injuryStatus": "IR",
    "injuryReason": "Olkapää",
    "reportedDate": "",
    "report": ""
  }
]